funparse/__init__.py
funparse/api.py
funparse/py.typed
funparse-0.2.4.dist-info/LICENSE
funparse-0.2.4.dist-info/METADATA
funparse-0.2.4.dist-info/WHEEL
funparse-0.2.4.dist-info/RECORD
