Metadata-Version: 2.1
Name: funparse
Version: 0.2.4
Summary: `funparse` allows you to 'derive' an argument parser from type annotations of a function's signature, cutting down on the boilerplate code.
Home-page: https://github.com/brunofauth/funparse
Keywords: cli,command-line,type,hint,derive,decorator
Author: Bruno Fauth
Author-email: 149593@upf.br
Requires-Python: >=3.11,<4.0
Classifier: Environment :: Console
Classifier: License :: OSI Approved :: MIT License
Classifier: Operating System :: OS Independent
Classifier: Programming Language :: Python :: 3
Classifier: Programming Language :: Python :: 3.11
Classifier: Topic :: Software Development :: Libraries
Classifier: Topic :: System :: Shells
Provides-Extra: docstring
Requires-Dist: docstring-parser (>=0.15,<0.16) ; extra == "docstring"
Project-URL: Bug Tracker, https://github.com/brunofauth/funparse/issues
Project-URL: Repository, https://github.com/brunofauth/funparse
